metasub_utils.zurich-0.2.0-py3.6-nspkg.pth
metasub_utils/zurich/__init__.py
metasub_utils/zurich/constants.py
metasub_utils/zurich/sftp_server.py
metasub_utils.zurich-0.2.0.dist-info/METADATA
metasub_utils.zurich-0.2.0.dist-info/RECORD
metasub_utils.zurich-0.2.0.dist-info/WHEEL
metasub_utils.zurich-0.2.0.dist-info/namespace_packages.txt
metasub_utils.zurich-0.2.0.dist-info/top_level.txt
